{
  "swfs": [
    {
      "location": "logo-anim.swf",
      "title": "Ruffle Logo",
      "author": "Ruffle contributors",
      "authorLink": "https://ruffle.rs",
      "config": {
        "autoplay": "on",
        "backgroundColor": "#31497D",
        "letterbox": "off",
        "unmuteOverlay": "hidden"
      }
    },
    {
      "location": "/swf/letter_A.swf",
      "title": "letter A",
      "author": "Little Fox",
      "authorLink": "https://little.fox",
      "type": "Animation"
    },
    {
      "location": "/swf/letter_B.swf",
      "title": "letter B",
      "author": "Little Fox",
      "authorLink": "https://little.fox",
      "type": "Animation"
    },
    {
      "location": "/swf/letter_C.swf",
      "title": "letter C",
      "author": "Little Fox",
      "authorLink": "https://little.fox",
      "type": "Animation"
    },
    {
      "location": "/swf/letter_D.swf",
      "title": "letter D",
      "author": "Little Fox",
      "authorLink": "https://little.fox",
      "type": "Animation"
    },
    {
      "location": "/swf/letter_E.swf",
      "title": "letter E",
      "author": "Little Fox",
      "authorLink": "https://little.fox",
      "type": "Animation"
    },
    {
      "location": "/swf/letter_F.swf",
      "title": "letter F",
      "author": "Little Fox",
      "authorLink": "https://little.fox",
      "type": "Animation"
    },
    {
      "location": "/swf/letter_G.swf",
      "title": "letter G",
      "author": "Little Fox",
      "authorLink": "https://little.fox",
      "type": "Animation"
    },
    {
      "location": "/swf/letter_H.swf",
      "title": "letter H",
      "author": "Little Fox",
      "authorLink": "https://little.fox",
      "type": "Animation"
    },
    {
      "location": "/swf/letter_I.swf",
      "title": "letter I",
      "author": "Little Fox",
      "authorLink": "https://little.fox",
      "type": "Animation"
    },
    {
      "location": "/swf/letter_J.swf",
      "title": "letter J",
      "author": "Little Fox",
      "authorLink": "https://little.fox",
      "type": "Animation"
    },
    {
      "location": "/swf/letter_K.swf",
      "title": "letter K",
      "author": "Little Fox",
      "authorLink": "https://little.fox",
      "type": "Animation"
    },
    {
      "location": "/swf/letter_L.swf",
      "title": "letter L",
      "author": "Little Fox",
      "authorLink": "https://little.fox",
      "type": "Animation"
    },
    {
      "location": "/swf/letter_M.swf",
      "title": "letter M",
      "author": "Little Fox",
      "authorLink": "https://little.fox",
      "type": "Animation"
    },
    {
      "location": "/swf/letter_N.swf",
      "title": "letter N",
      "author": "Little Fox",
      "authorLink": "https://little.fox",
      "type": "Animation"
    },
    {
      "location": "/swf/letter_O.swf",
      "title": "letter O",
      "author": "Little Fox",
      "authorLink": "https://little.fox",
      "type": "Animation"
    },
    {
      "location": "/swf/letter_P.swf",
      "title": "letter P",
      "author": "Little Fox",
      "authorLink": "https://little.fox",
      "type": "Animation"
    },
    {
      "location": "/swf/letter_Q.swf",
      "title": "letter Q",
      "author": "Little Fox",
      "authorLink": "https://little.fox",
      "type": "Animation"
    },
    {
      "location": "/swf/letter_R.swf",
      "title": "letter R",
      "author": "Little Fox",
      "authorLink": "https://little.fox",
      "type": "Animation"
    },
    {
      "location": "/swf/letter_S.swf",
      "title": "letter S",
      "author": "Little Fox",
      "authorLink": "https://little.fox",
      "type": "Animation"
    },
    {
      "location": "/swf/letter_T.swf",
      "title": "letter T",
      "author": "Little Fox",
      "authorLink": "https://little.fox",
      "type": "Animation"
    }, 
    {
      "location": "/swf/letter_U.swf",
      "title": "letter U",
      "author": "Little Fox",
      "authorLink": "https://little.fox",
      "type": "Animation"
    },
    {
      "location": "/swf/letter_V.swf",
      "title": "letter V",
      "author": "Little Fox",
      "authorLink": "https://little.fox",
      "type": "Animation"
    },
    {
      "location": "/swf/letter_W.swf",
      "title": "letter W",
      "author": "Little Fox",
      "authorLink": "https://little.fox",
      "type": "Animation"
    },
    {
      "location": "/swf/letter_X.swf",
      "title": "letter X",
      "author": "Little Fox",
      "authorLink": "https://little.fox",
      "type": "Animation"
    },
    {
      "location": "/swf/letter_Y.swf",
      "title": "letter Y",
      "author": "Little Fox",
      "authorLink": "https://little.fox",
      "type": "Animation"
    },
    {
      "location": "/swf/letter_Z.swf",
      "title": "letter Z",
      "author": "Little Fox",
      "authorLink": "https://little.fox",
      "type": "Animation"
    },
    
    {
      "location": "swfs/alien_hominid.swf",
      "title": "Alien Hominid",
      "author": "Tom Fulp and Dan Paladin",
      "authorLink": "https://www.newgrounds.com",
      "type": "Game"
    },
    {
      "location": "swfs/flyguy.swf",
      "title": "FlyGuy",
      "author": "Trevor van Meter",
      "authorLink": "https://www.heytvm.com",
      "type": "Game"
    },
    {
      "location": "swfs/marvin_spectrum.swf",
      "title": "Marvin Spectrum",
      "author": "Bryan Singh",
      "authorLink": "https://www.hotbryan.com",
      "type": "Game"
    },
    {
      "location": "swfs/wasted_sky.swf",
      "title": "Wasted Sky",
      "author": "Tom Fulp",
      "authorLink": "https://www.newgrounds.com",
      "type": "Game"
    }
  ]
}
